{
  "name": "corporate-ftp-server-penetration",
  "title": "Corporate FTP Server Penetration",
  "description": "A corporate FTP server contains sensitive employee data and confidential files. The server has realistic directory structures, user accounts, and security misconfigurations typical of real-world environments.",
  "category": "network",
  "subcategories": [
    "network"
  ],
  "difficulty": "medium",
  "flag": "CTF{network_h7oxgd1t1o2i}",
  "machines": 2,
  "machineDetails": [
    {
      "name": "ftp-server",
      "type": "victim",
      "ip": "172.23.199.103",
      "services": [
        "ftp",
        "ssh"
      ]
    },
    {
      "name": "attacker-machine",
      "type": "attacker",
      "ip": "172.23.199.3",
      "services": [
        "ssh"
      ]
    }
  ],
  "stages": 5,
  "created": "2025-12-29T18:01:12.503Z",
  "generator": "universal-structure-agent"
}